inspect4py/__init__.py
inspect4py/cli.py
inspect4py/parse_setup_files.py
inspect4py/structure_tree.py
inspect4py/utils.py
inspect4py/licenses/0bsd.txt
inspect4py/licenses/afl-3.0.txt
inspect4py/licenses/agpl-3.0.txt
inspect4py/licenses/apache-2.0.txt
inspect4py/licenses/artistic-2.0.txt
inspect4py/licenses/bsd-2-clause.txt
inspect4py/licenses/bsd-3-clause-clear.txt
inspect4py/licenses/bsd-3-clause.txt
inspect4py/licenses/bsd-4-clause.txt
inspect4py/licenses/bsl-1.0.txt
inspect4py/licenses/cc-by-4.0.txt
inspect4py/licenses/cc-by-sa-4.0.txt
inspect4py/licenses/cc0-1.0.txt
inspect4py/licenses/cecill-2.1.txt
inspect4py/licenses/cern-ohl-p-2.0.txt
inspect4py/licenses/cern-ohl-s-2.0.txt
inspect4py/licenses/cern-ohl-w-2.0.txt
inspect4py/licenses/ecl-2.0.txt
inspect4py/licenses/epl-1.0.txt
inspect4py/licenses/epl-2.0.txt
inspect4py/licenses/eupl-1.1.txt
inspect4py/licenses/eupl-1.2.txt
inspect4py/licenses/gpl-2.0.txt
inspect4py/licenses/gpl-3.0.txt
inspect4py/licenses/isc.txt
inspect4py/licenses/lgpl-2.1.txt
inspect4py/licenses/lgpl-3.0.txt
inspect4py/licenses/lppl-1.3c.txt
inspect4py/licenses/mit-0.txt
inspect4py/licenses/mit.txt
inspect4py/licenses/mpl-2.0.txt
inspect4py/licenses/ms-pl.txt
inspect4py/licenses/ms-rl.txt
inspect4py/licenses/mulanpsl-2.0.txt
inspect4py/licenses/ncsa.txt
inspect4py/licenses/odbl-1.0.txt
inspect4py/licenses/ofl-1.1.txt
inspect4py/licenses/osl-3.0.txt
inspect4py/licenses/postgresql.txt
inspect4py/licenses/unlicense.txt
inspect4py/licenses/upl-1.0.txt
inspect4py/licenses/vim.txt
inspect4py/licenses/wtfpl.txt
inspect4py/licenses/zlib.txt
inspect4py/staticfg/__init__.py
inspect4py/staticfg/builder.py
inspect4py/staticfg/model.py
test/__init__.py
test/test_inspect4py.py
test/test_utils.py
test/test_files/__init__.py
test/test_files/test_data_flow.py
test/test_files/test_random.py
test/test_files/demo/__init__.py
test/test_files/demo/demo_example_argparse.py
test/test_files/demo/demo_example_class.py
test/test_files/demo/demo_example_func_main.py
inspect4py-0.0.7.dist-info/LICENSE
inspect4py-0.0.7.dist-info/METADATA
inspect4py-0.0.7.dist-info/WHEEL
inspect4py-0.0.7.dist-info/entry_points.txt
inspect4py-0.0.7.dist-info/top_level.txt
inspect4py-0.0.7.dist-info/RECORD
