Metadata-Version: 2.1
Name: inspect4py
Version: 0.0.7
Summary: Static code analysis package for Python repositories
Home-page: https://github.com/SoftwareUnderstanding/inspect4py
Author: Rosa Filgueira and Daniel Garijo
License: BSD-3-Clause
Platform: UNKNOWN
Classifier: Development Status :: 3 - Alpha
Classifier: Programming Language :: Python
Requires-Python: >=3.6
License-File: LICENSE
Requires-Dist: docstring-parser (==0.7)
Requires-Dist: astor
Requires-Dist: graphviz
Requires-Dist: click
Requires-Dist: pigar
Requires-Dist: setuptools (==54.2.0)
Requires-Dist: json2html
Requires-Dist: configparser
Requires-Dist: bigcode-astgen
Requires-Dist: GitPython
Requires-Dist: tree-sitter
